chatweather/__init__.py
chatweather/chatbot.py
chatweather/config.py
chatweather/weather.py
chatweather/weather_api_datetime.py
chatweather/__pycache__/__init__.cpython-38.pyc
chatweather/__pycache__/chatbot.cpython-38.pyc
chatweather/__pycache__/config.cpython-38.pyc
chatweather/__pycache__/weather.cpython-38.pyc
chatweather/__pycache__/weather_api_datetime.cpython-38.pyc
chatweather-0.1.9.dist-info/LICENSE
chatweather-0.1.9.dist-info/METADATA
chatweather-0.1.9.dist-info/WHEEL
chatweather-0.1.9.dist-info/top_level.txt
chatweather-0.1.9.dist-info/RECORD
