Metadata-Version: 2.1
Name: chatweather
Version: 0.1.9
Summary: A package for weather forecasting and ChatGPT integration
Home-page: https://github.com/daisybum/pyWeather
Author: SanghyunPark
Author-email: hirvahapjh@gmail.com
License: UNKNOWN
Platform: UNKNOWN
Classifier: Development Status :: 3 - Alpha
Classifier: Intended Audience :: Developers
Classifier: License :: OSI Approved :: Apache Software License
Classifier: Operating System :: OS Independent
Classifier: Programming Language :: Python :: 3
Classifier: Programming Language :: Python :: 3.8
Classifier: Programming Language :: Python :: 3.9
Requires-Python: >=3.8
Requires-Dist: requests
Requires-Dist: xmltodict
Requires-Dist: openai==1.52.2
Requires-Dist: pytest==8.3.3
